hexin/__init__.py
hexin-0.1.dist-info/METADATA
hexin-0.1.dist-info/WHEEL
hexin-0.1.dist-info/top_level.txt
hexin-0.1.dist-info/RECORD
