Metadata-Version: 2.1
Name: hexin
Version: 0.1
Summary: The boss of MARS Church
Home-page: UNKNOWN
Author: marsggbo
Author-email: csxinhe@comp.hkbu.edu.hk
License: UNKNOWN
Platform: UNKNOWN
Classifier: Programming Language :: Python :: 3
Classifier: License :: OSI Approved :: MIT License
Classifier: Operating System :: OS Independent
Requires-Python: >=3.6
